pymokugame/__init__.py
pymokugame/pymokugame.py
pymokugame-1.0.2.dist-info/LICENSE
pymokugame-1.0.2.dist-info/METADATA
pymokugame-1.0.2.dist-info/WHEEL
pymokugame-1.0.2.dist-info/entry_points.txt
pymokugame-1.0.2.dist-info/top_level.txt
pymokugame-1.0.2.dist-info/RECORD
